PyModuleGenerator
