Metadata-Version: 2.1
Name: PyModuleGenerator
Version: 1.1.0
Summary: A simple python module generator
Home-page: https://github.com/ProfesseurIssou/PyModuleGenerator
Author: Alix Hamidou
Author-email: alix.hamidou@gmail.com
License: MIT
Classifier: Development Status :: 4 - Beta
Classifier: Intended Audience :: Developers
Classifier: License :: OSI Approved :: MIT License
Classifier: Operating System :: Microsoft :: Windows
Classifier: Operating System :: Unix
Classifier: Programming Language :: Python :: 3
Classifier: Topic :: Software Development :: Build Tools
Classifier: Topic :: Software Development :: Libraries :: Python Modules
